{
  "movies": [
    {
      "id": 1,
      "Title": "Test 1",
      "Description": "Lorem ipsum dolor sit amet, consectetur adipisicing elit. Eius accusantium id dolores, eaque corporis consequuntur, possimus, incidunt esse recusandae nam amet mollitia suscipit aliquid laborum voluptates iure maxime ducimus dolorem?",
      "Image": "1.jpeg",
      "CategoryId": 1,
      "DatePublished": "2021-12-22T10:17:26.637Z",
      "IsPopular": false
    },
    {
      "id": 2,
      "Title": "Test 2",
      "Description": "Lorem ipsum dolor sit amet, consectetur adipisicing elit. Eius accusantium id dolores, eaque corporis consequuntur, possimus, incidunt esse recusandae nam amet mollitia suscipit aliquid laborum voluptates iure maxime ducimus dolorem?",
      "Image": "2.jpeg",
      "CategoryId": 2,
      "DatePublished": "2021-12-22T10:17:26.637Z",
      "IsPopular": false
    },
    {
      "id": 3,
      "Title": "Test 3",
      "Description": "Lorem ipsum dolor sit amet, consectetur adipisicing elit. Eius accusantium id dolores, eaque corporis consequuntur, possimus, incidunt esse recusandae nam amet mollitia suscipit aliquid laborum voluptates iure maxime ducimus dolorem?",
      "Image": "3.jpeg",
      "CategoryId": 4,
      "DatePublished": "2021-12-22T10:17:26.637Z",
      "IsPopular": false
    },
    {
      "id": 4,
      "Title": "Test 4",
      "Description": "Lorem ipsum dolor sit amet, consectetur adipisicing elit. Eius accusantium id dolores, eaque corporis consequuntur, possimus, incidunt esse recusandae nam amet mollitia suscipit aliquid laborum voluptates iure maxime ducimus dolorem?",
      "Image": "4.jpeg",
      "CategoryId": 2,
      "DatePublished": "2021-12-22T10:17:26.637Z",
      "IsPopular": false
    },
    {
      "id": 5,
      "Title": "Test 5",
      "Description": "Lorem ipsum dolor sit amet, consectetur adipisicing elit. Eius accusantium id dolores, eaque corporis consequuntur, possimus, incidunt esse recusandae nam amet mollitia suscipit aliquid laborum voluptates iure maxime ducimus dolorem?",
      "Image": "5.jpeg",
      "CategoryId": 5,
      "DatePublished": "2021-12-22T10:17:26.637Z",
      "IsPopular": false
    }
  ],
  "categories": [
    {
      "Id": 1,
      "Name": "Macera"
    },
    {
      "Id": 2,
      "Name": "Romantik"
    },
    {
      "Id": 3,
      "Name": "Komedi"
    },
    {
      "Id": 4,
      "Name": "Dram"
    },
    {
      "Id": 5,
      "Name": "Şavaş"
    }
  ]
}